generic_service/__init__.py
generic_service/py.typed
generic_service/service.py
generic_service-0.0.0.dev0.dist-info/LICENSE.txt
generic_service-0.0.0.dev0.dist-info/METADATA
generic_service-0.0.0.dev0.dist-info/WHEEL
generic_service-0.0.0.dev0.dist-info/top_level.txt
generic_service-0.0.0.dev0.dist-info/RECORD
